README.rst
setup.py
slocum/__init__.py
slocum/poseidon.py
slocum/run.py
slocum/windbreaker.py
slocum.egg-info/PKG-INFO
slocum.egg-info/SOURCES.txt
slocum.egg-info/dependency_links.txt
slocum.egg-info/entry_points.txt
slocum.egg-info/not-zip-safe
slocum.egg-info/requires.txt
slocum.egg-info/top_level.txt
slocum/lib/__init__.py
slocum/lib/conventions.py
slocum/lib/emaillib.py
slocum/lib/enslib.py
slocum/lib/griblib.py
slocum/lib/objects.py
slocum/lib/rtefcst.py
slocum/lib/saildocs.py
slocum/lib/tinylib.py
slocum/lib/units.py
slocum/lib/visualize.py
test/test_objects.py
test/test_poseidon.py
test/test_regression.py
test/test_rtefcst.py
test/test_saildocs.py
test/test_tinylib.py