Metadata-Version: 1.1
Name: slocum
Version: 0.1.3
Summary: Slocum -- A tool for getting smaller better forecasts to sailors
Home-page: http://github.com/akleeman/slocum
Author: Alex Kleeman and Markus Schweitzer
Author-email: akleeman@gmail.com
License: MIT
Platform: UNKNOWN
Classifier: Development Status :: 3 - Alpha
Classifier: License :: OSI Approved :: MIT License
Classifier: Programming Language :: Python :: 2.7
